testscript_eval/__init__.py
testscript_eval/assertation.py
testscript_eval/eval.py
testscript_eval/misc.py
testscript_eval/operations.py
testscript_eval/pytest_plugin.py
testscript_eval-0.0.4.dist-info/entry_points.txt
testscript_eval-0.0.4.dist-info/LICENSE
testscript_eval-0.0.4.dist-info/WHEEL
testscript_eval-0.0.4.dist-info/METADATA
testscript_eval-0.0.4.dist-info/RECORD
